mantisshrimp/__init__.py
mantisshrimp/all.py
mantisshrimp/imports.py
mantisshrimp/core/__init__.py
mantisshrimp/core/bbox.py
mantisshrimp/core/category.py
mantisshrimp/core/id_map.py
mantisshrimp/core/mask.py
mantisshrimp/data/__init__.py
mantisshrimp/data/dataset.py
mantisshrimp/data_preparer/__init__.py
mantisshrimp/data_preparer/data_preparer.py
mantisshrimp/data_preparer/mixins.py
mantisshrimp/metrics/__init__.py
mantisshrimp/metrics/metric.py
mantisshrimp/metrics/coco_metric/__init__.py
mantisshrimp/metrics/coco_metric/coco_eval.py
mantisshrimp/metrics/coco_metric/coco_metric.py
mantisshrimp/metrics/coco_metric/coco_utils.py
mantisshrimp/metrics/coco_metric/reference_utils.py
mantisshrimp/models/__init__.py
mantisshrimp/models/detr_demo.py
mantisshrimp/models/mantis_detr.py
mantisshrimp/models/mantis_module.py
mantisshrimp/models/parameters_splits_module_mixin.py
mantisshrimp/models/utils.py
mantisshrimp/models/mantis_rcnn/__init__.py
mantisshrimp/models/mantis_rcnn/build_training_sample_rcnn_mixin.py
mantisshrimp/models/mantis_rcnn/mantis_faster_rcnn.py
mantisshrimp/models/mantis_rcnn/mantis_mask_rcnn.py
mantisshrimp/models/mantis_rcnn/mantis_rcnn.py
mantisshrimp/models/mantis_rcnn/rcnn_param_groups.py
mantisshrimp/parsers/__init__.py
mantisshrimp/parsers/combined_parser.py
mantisshrimp/parsers/defaults.py
mantisshrimp/parsers/parser.py
mantisshrimp/parsers/splits.py
mantisshrimp/parsers/coco_parsers/__init__.py
mantisshrimp/parsers/coco_parsers/coco_annotation_parser.py
mantisshrimp/parsers/coco_parsers/coco_image_info_parser.py
mantisshrimp/parsers/mixins/__init__.py
mantisshrimp/parsers/mixins/parser_mixins.py
mantisshrimp/test_utils/__init__.py
mantisshrimp/test_utils/samples.py
mantisshrimp/test_utils/simple_model.py
mantisshrimp/transforms/__init__.py
mantisshrimp/transforms/albu_transform.py
mantisshrimp/transforms/transform.py
mantisshrimp/utils/__init__.py
mantisshrimp/utils/get_files.py
mantisshrimp/utils/imageio.py
mantisshrimp/utils/torch_utils.py
mantisshrimp-0.0.8.dist-info/LICENSE
mantisshrimp-0.0.8.dist-info/METADATA
mantisshrimp-0.0.8.dist-info/WHEEL
mantisshrimp-0.0.8.dist-info/entry_points.txt
mantisshrimp-0.0.8.dist-info/top_level.txt
mantisshrimp-0.0.8.dist-info/RECORD
