Metadata-Version: 2.1
Name: mantisshrimp
Version: 0.0.8
Summary: Object detection framework
Home-page: https://github.com/lgvaz/mantisshrimp/tree/master/
Author: Lucas Goulart Vazquez
Author-email: lgvaz42@gmail.com
License: Apache Software License 2.0
Keywords: object-detection
Platform: UNKNOWN
Classifier: Development Status :: 3 - Alpha
Classifier: Intended Audience :: Developers
Classifier: License :: OSI Approved :: Apache Software License
Classifier: Natural Language :: English
Classifier: Programming Language :: Python :: 3.6
Classifier: Programming Language :: Python :: 3.7
Classifier: Programming Language :: Python :: 3.8
Requires-Python: >=3.6
Requires-Dist: fastcore
Requires-Dist: pytorch-lightning
Requires-Dist: opencv-python
